{
    "meta": {
        "title": "Łukasz Kostyk - Portfolio",
        "description": "Witaj w moim interaktywnym portfolio z najnowszymi projektami."
    },
    "navigation": {
        "close": "Zamknij [X]",
        "about": "O Mnie",
        "change_language": "Zmień Język",
        "projects": "Projekty",
        "contact": "Kontakt"
    },
    "hero": {
        "name": "ŁUKASZ KOSTYK",
        "position": {
            "title": "Jestem",
            "value": "Full-Stack Developerem"
        },
        "location": {
            "title": "mieszkającym w",
            "value": "Gdyni"
        },
        "cta_button": "Rozpocznij przejażdżkę"
    },
    "projects": {
        "title": "Przystanek: Moje Projekty",
        "linkLabel": "Zobacz więcej",
        "kkol": {
            "title": "Karwińska Olimpiada",
            "description": "Oficjalna platforma do śledzenia i zarządzania turniejami z serii Karwińska Olimpiada - corocznej serii turniejów."
        },
        "dartES": {
            "title": "DartES",
            "description": "Aplikacja do darta. Śledź wynik meczu oraz szczegółowe statystyki. Zintegrowana tablica wyników do użycia przy profesjonalnych transmisjach na żywo."
        }
    },
    "about": {
        "title": "Przystanek: O Mnie",
        "content": "Lorem ipsum ALE PO POLSKU dolor sit amet consectetur, adipisicing elit. Expedita assumenda quaerat sapiente aut eos iure. Tempora eligendi reiciendis consequuntur repellendus dolor laboriosam eveniet, hic numquam sed natus deserunt facere nemo?"
    }
}